{
  "meta": {
    "id": 4570,
    "title": "Përgjimet zbulojnë rolin e krimit të organizuar në blerjen e votave",
    "slug": "pergjimet-zbulojne-rolin-e-krimit-te-organizuar-ne-blerjen-e-votave",
    "category_id": 6,
    "created_at": "2019-01-30T19:42:02.778Z",
    "tags": [],
    "posts_count": 30,
    "views": 2484,
    "like_count": 7,
    "word_count": 827
  },
  "posts": [
    {
      "id": 83215,
      "post_number": 1,
      "username": "gjembi",
      "name": "Gjembi",
      "avatar_template": "/user_avatar/peshkupauje.com/gjembi/{size}/216_2.png",
      "created_at": "2019-01-30T19:42:02.888Z",
      "cooked": "<aside class=\"onebox whitelistedgeneric\">\n  <header class=\"source\">\n      <a href=\"https://www.reporter.al/pergjimet-zbulojne-rolin-e-krimit-te-organizuar-ne-blerjen-e-votave/\" target=\"_blank\" title=\"07:12PM - 30 January 2019\" rel=\"nofollow noopener\">reporter.al – 30 Jan 19</a>\n  </header>\n  <article class=\"onebox-body\">\n    <div class=\"aspect-image\" style=\"--aspect-ratio:800/450;\"><img src=\"https://peshkupauje.com/uploads/default/original/2X/9/95370328fac059504dfda7fde8ff1f4fbd8e16f5.jpeg\" class=\"thumbnail\"></div>\n\n<h3><a href=\"https://www.reporter.al/pergjimet-zbulojne-rolin-e-krimit-te-organizuar-ne-blerjen-e-votave/\" target=\"_blank\" rel=\"nofollow noopener\">Përgjimet zbulojnë rolin e krimit të organizuar në blerjen e votave -...</a></h3>\n\n<p>Dhjetra përgjime dhe dokumente të siguruara nga BIRN përmes dy hetimeve në Prokurorinë e Krimeve të Rënda hedhin dritë mbi përfshirjen e krimit të organizuar në episode të blerjes së votës në Durrës, Kavajë, Lezhë dhe Dibër, ndërkohë që Shqipëria po...</p>\n\n\n  </article>\n  <div class=\"onebox-metadata\">\n    \n    \n  </div>\n  <div style=\"clear: both\"></div>\n</aside>\n",
      "reply_to_post_number": null,
      "like_count": 0
    },
    {
      "id": 83217,
      "post_number": 2,
      "username": "varik",
      "name": "varianti kohor",
      "avatar_template": "/user_avatar/peshkupauje.com/varik/{size}/115_2.png",
      "created_at": "2019-01-30T20:09:27.119Z",
      "cooked": "<p>keshtu e ka rilidja, prandaj sben hajer luli i vocerr</p>",
      "reply_to_post_number": null,
      "like_count": 0
    },
    {
      "id": 83218,
      "post_number": 3,
      "username": "Pjer",
      "name": "Pjer Thomas",
      "avatar_template": "/letter_avatar_proxy/v4/letter/p/ecb155/{size}.png",
      "created_at": "2019-01-30T20:16:09.874Z",
      "cooked": "<p>nese ka prova qe jane blere apo vjedhur votat, ketu i bie qe prokuroria te arrestoje te dyja palet, edhe porositesin (perfituesin) e votave qe i bie te jete Daku, edhe sekseret e votave, qe i bie te jene Avdylet.</p>",
      "reply_to_post_number": null,
      "like_count": 0
    },
    {
      "id": 83219,
      "post_number": 4,
      "username": "gjembi",
      "name": "Gjembi",
      "avatar_template": "/user_avatar/peshkupauje.com/gjembi/{size}/216_2.png",
      "created_at": "2019-01-30T20:23:31.982Z",
      "cooked": "<p>Tamam ashtu tha dhe Nard Ndoka!</p>",
      "reply_to_post_number": 3,
      "like_count": 0
    },
    {
      "id": 83220,
      "post_number": 5,
      "username": "InkuizitoriMoth",
      "name": "..... ......",
      "avatar_template": "/user_avatar/peshkupauje.com/inkuizitorimoth/{size}/7035_2.png",
      "created_at": "2019-01-30T20:31:43.143Z",
      "cooked": "<p>Pjer, policia po qe e zonja le te gjeje po desh pse une (dhe jo vetem une, por edhe shum te tjere qe kom pyt) kam nje ndjenje turpi dhe frike se mos me quajne vjedhhajdut, kur kaloj, pa blere gje (sigurisht edhe pa vjedh gje), ne shtegun e daljes se supermerkatit ku jane shitset qe kontrollojne mallin e blere me aparatet lazer qe bejne pip-pip-pip.</p>",
      "reply_to_post_number": 3,
      "like_count": 0
    },
    {
      "id": 83221,
      "post_number": 6,
      "username": "Pjer",
      "name": "Pjer Thomas",
      "avatar_template": "/letter_avatar_proxy/v4/letter/p/ecb155/{size}.png",
      "created_at": "2019-01-30T20:50:50.334Z",
      "cooked": "<p>nuk te kuptova i modho, çfar do te thuash,</p>",
      "reply_to_post_number": 5,
      "like_count": 0
    },
    {
      "id": 83222,
      "post_number": 7,
      "username": "InkuizitoriMoth",
      "name": "..... ......",
      "avatar_template": "/user_avatar/peshkupauje.com/inkuizitorimoth/{size}/7035_2.png",
      "created_at": "2019-01-30T20:53:16.544Z",
      "cooked": "<p>ndoshta e ka kuptu gjembi e te ndihmon dhe ty te kuptosh.</p>",
      "reply_to_post_number": 6,
      "like_count": 0
    },
    {
      "id": 83223,
      "post_number": 8,
      "username": "Pjer",
      "name": "Pjer Thomas",
      "avatar_template": "/letter_avatar_proxy/v4/letter/p/ecb155/{size}.png",
      "created_at": "2019-01-30T21:08:30.816Z",
      "cooked": "<p>po u fillua me ironi e te perfundoi me sarkazem, kshu s’ka gjo ne vije tema dhe forumi,</p>",
      "reply_to_post_number": 7,
      "like_count": 0
    },
    {
      "id": 83224,
      "post_number": 9,
      "username": "InkuizitoriMoth",
      "name": "..... ......",
      "avatar_template": "/user_avatar/peshkupauje.com/inkuizitorimoth/{size}/7035_2.png",
      "created_at": "2019-01-30T22:21:35.778Z",
      "cooked": "<p>jo vetem tema dhe forumi, por kshu nuk kane gjo ne vije as votimet e lira demokratike te garantuara nga policia.</p>",
      "reply_to_post_number": 8,
      "like_count": 0
    },
    {
      "id": 83225,
      "post_number": 10,
      "username": "dafne",
      "name": "Dafne",
      "avatar_template": "/user_avatar/peshkupauje.com/dafne/{size}/4008_2.png",
      "created_at": "2019-01-30T22:45:00.263Z",
      "cooked": "<p>asgje e re nga fronti i lindjes …</p>",
      "reply_to_post_number": null,
      "like_count": 0
    },
    {
      "id": 83232,
      "post_number": 11,
      "username": "Patrioti",
      "name": "patrioti",
      "avatar_template": "/letter_avatar_proxy/v4/letter/p/2bfe46/{size}.png",
      "created_at": "2019-01-31T02:57:40.266Z",
      "cooked": "<p>Ate xhuxhin ta fusin te qelia qe la Lul Berisha, po si shumhera ne AL ska per te ndodh gjo. Luli spo e permend mo gjushin si vjedhesin me te modh te votes se lire. Gojet e liga thone se gjushi i ka rregullu telat me ca leje ndertimi.</p>",
      "reply_to_post_number": null,
      "like_count": 0
    },
    {
      "id": 83246,
      "post_number": 12,
      "username": "varik",
      "name": "varianti kohor",
      "avatar_template": "/user_avatar/peshkupauje.com/varik/{size}/115_2.png",
      "created_at": "2019-01-31T18:48:48.104Z",
      "cooked": "<p>nuk burgos dot 30% te popullit, se ben dot</p>\n<p>peshqit e medhenj kane koqe te medha, e po spate koqe me te medha se ata, si burgos dot</p>\n<p>do ta haje ndonje peshk i vogel si gjithmone</p>",
      "reply_to_post_number": 3,
      "like_count": 0
    },
    {
      "id": 92362,
      "post_number": 13,
      "username": "gjembi",
      "name": "Gjembi",
      "avatar_template": "/user_avatar/peshkupauje.com/gjembi/{size}/216_2.png",
      "created_at": "2019-06-06T20:28:24.842Z",
      "cooked": "<p>Rifreskim.</p>",
      "reply_to_post_number": null,
      "like_count": 0
    },
    {
      "id": 92356,
      "post_number": 14,
      "username": "gjembi",
      "name": "Gjembi",
      "avatar_template": "/user_avatar/peshkupauje.com/gjembi/{size}/216_2.png",
      "created_at": "2019-06-06T20:11:41.204Z",
      "cooked": "<p>C’behet andej nga Shqiperia? E futen ne burg Dakon? Dha doreheqjen Kryeministri?</p>",
      "reply_to_post_number": null,
      "like_count": 0
    },
    {
      "id": 92358,
      "post_number": 15,
      "username": "STALKER",
      "name": "",
      "avatar_template": "/user_avatar/peshkupauje.com/stalker/{size}/2135_2.png",
      "created_at": "2019-06-06T20:21:59.249Z",
      "cooked": "<p>Hanibal ante portam:</p>\n<aside class=\"onebox whitelistedgeneric\">\n  <header class=\"source\">\n      <a href=\"https://www.javanews.al/pergjimet-dako-nuk-jam-duke-folur-me-astrit-avdulajn-eshte-manipuluar/\" target=\"_blank\" rel=\"nofollow noopener\">Javanews.al</a>\n  </header>\n  <article class=\"onebox-body\">\n    <div class=\"aspect-image\" style=\"--aspect-ratio:800/402;\"><img src=\"https://peshkupauje.com/uploads/default/original/2X/f/f6633e5f614b45038c3c231aa920112d55488504.jpeg\" class=\"thumbnail\"></div>\n\n<h3><a href=\"https://www.javanews.al/pergjimet-dako-nuk-jam-duke-folur-me-astrit-avdulajn-eshte-manipuluar/\" target=\"_blank\" rel=\"nofollow noopener\">Përgjimet/ Dako: Nuk jam duke folur me Astrit Avdulajn, është manipuluar</a></h3>\n\n<p>Kryetari i Bashkisë Durrësit, Vangjush Dako, ka folur sot rreth përgjimeve të publikuara nga “Bild”, ku ky i fundit del në këto përgjime duke folur me Astrit Avdylajn, kreun e bandës së Shijakut. I ftuar në emisionin “Opinion”, Dako ka mohuar të ketë...</p>\n\n\n  </article>\n  <div class=\"onebox-metadata\">\n    \n    \n  </div>\n  <div style=\"clear: both\"></div>\n</aside>\n",
      "reply_to_post_number": null,
      "like_count": 0
    },
    {
      "id": 92359,
      "post_number": 16,
      "username": "STALKER",
      "name": "",
      "avatar_template": "/user_avatar/peshkupauje.com/stalker/{size}/2135_2.png",
      "created_at": "2019-06-06T20:22:52.580Z",
      "cooked": "<p>Hajdarmataj kshu…</p>\n<aside class=\"onebox whitelistedgeneric\">\n  <header class=\"source\">\n      <a href=\"https://www.javanews.al/339-u-perdor-per-biznes-brace-nxjerr-emrin-e-prokurorit-shiti-pergjimet/\" target=\"_blank\" rel=\"nofollow noopener\">Javanews.al</a>\n  </header>\n  <article class=\"onebox-body\">\n    <div class=\"aspect-image\" style=\"--aspect-ratio:800/533;\"><img src=\"https://peshkupauje.com/uploads/default/original/2X/f/fb2a3d05d43d3f35691a8e9a3e2c4e06c3dc36cd.jpeg\" class=\"thumbnail\"></div>\n\n<h3><a href=\"https://www.javanews.al/339-u-perdor-per-biznes-brace-nxjerr-emrin-e-prokurorit-shiti-pergjimet/\" target=\"_blank\" rel=\"nofollow noopener\">339 u përdor për biznes/ Braçe nxjerr emrin e prokurorit: Shiti përgjimet</a></h3>\n\n<p>Zv/kryeministri Erion Braçe, deklaroi në emisionin Open të Eni Vasilit se përgjimet e publikuara janë punë e përditshme e prokurorisë, por dikush ka bërë biznes personal me dosjen. “Askush nuk ka hetuar. Kjo dosje ka nisur në dhjetor të vitit 2016...</p>\n\n\n  </article>\n  <div class=\"onebox-metadata\">\n    \n    \n  </div>\n  <div style=\"clear: both\"></div>\n</aside>\n",
      "reply_to_post_number": 15,
      "like_count": 0
    },
    {
      "id": 92360,
      "post_number": 17,
      "username": "gjembi",
      "name": "Gjembi",
      "avatar_template": "/user_avatar/peshkupauje.com/gjembi/{size}/216_2.png",
      "created_at": "2019-06-06T20:25:26.122Z",
      "cooked": "<p>Kjo te mundon dhe ty, kush i nxorri pergjimet?</p>",
      "reply_to_post_number": 16,
      "like_count": 0
    },
    {
      "id": 92361,
      "post_number": 18,
      "username": "STALKER",
      "name": "",
      "avatar_template": "/user_avatar/peshkupauje.com/stalker/{size}/2135_2.png",
      "created_at": "2019-06-06T20:26:59.798Z",
      "cooked": "<p>Qofte dhe pse anonimë: fakti qe unë po të permend emrin ‘gjembi’, të bën ty fajtore për ndonje gje?</p>",
      "reply_to_post_number": 17,
      "like_count": 0
    },
    {
      "id": 92363,
      "post_number": 19,
      "username": "Alba2265",
      "name": "",
      "avatar_template": "/letter_avatar_proxy/v4/letter/a/85e7bf/{size}.png",
      "created_at": "2019-06-06T20:32:57.007Z",
      "cooked": "<p>“Ekspertet” do e nxjerrin videon te manipuluar.dako president.</p>",
      "reply_to_post_number": 14,
      "like_count": 0
    },
    {
      "id": 92364,
      "post_number": 20,
      "username": "gjembi",
      "name": "Gjembi",
      "avatar_template": "/user_avatar/peshkupauje.com/gjembi/{size}/216_2.png",
      "created_at": "2019-06-06T20:33:55.169Z",
      "cooked": "<p>Ah, pse vetem emrin i permenden Dakos? E paskam marre vesh gabim.</p>\n<p><em>Kjo te mundon dhe ty, kush i nxorri pergjimet?</em></p>",
      "reply_to_post_number": 18,
      "like_count": 0
    },
    {
      "id": 92366,
      "post_number": 21,
      "username": "STALKER",
      "name": "",
      "avatar_template": "/user_avatar/peshkupauje.com/stalker/{size}/2135_2.png",
      "created_at": "2019-06-06T20:50:48.911Z",
      "cooked": "<p>Personi në fjale sot eshte në burg. Ndersa i perfoluri në dosjen e skaduar prej 2 vjetesh tha:</p>\n<aside class=\"onebox whitelistedgeneric\">\n  <header class=\"source\">\n      <a href=\"https://www.javanews.al/ne-nuk-duam-te-humbim-asnje-vote-dako-per-astrit-avdylajn-se-kam-njohur-kurre-pas-2016-e-kam-takuar-si-qytetaret-e-tjere/\" target=\"_blank\" rel=\"nofollow noopener\">Javanews.al</a>\n  </header>\n  <article class=\"onebox-body\">\n    <div class=\"aspect-image\" style=\"--aspect-ratio:780/440;\"><img src=\"https://peshkupauje.com/uploads/default/original/2X/1/11a37ef9535ed47625cdd549eb3be39492231869.jpeg\" class=\"thumbnail\"></div>\n\n<h3><a href=\"https://www.javanews.al/ne-nuk-duam-te-humbim-asnje-vote-dako-per-astrit-avdylajn-se-kam-njohur-kurre-pas-2016-e-kam-takuar-si-qytetaret-e-tjere/\" target=\"_blank\" rel=\"nofollow noopener\">Ne nuk duam të humbim asnjë vote/ Dako për Astrit Avdylajn: Se kam njohur...</a></h3>\n\n<p>Kreu i Bashkisë së Durrësit, Vangjush Dako, duke komentuar përgjimet e publikuara nga “BILD”, i pyetur se si një kryetar bashkie ja hap telefonin çdo njeriu, ka thënë se në kohë fushate, ja hap të gjithëve telefonin, sepse nuk duan të humbasin asnjë...</p>\n\n\n  </article>\n  <div class=\"onebox-metadata\">\n    \n    \n  </div>\n  <div style=\"clear: both\"></div>\n</aside>\n",
      "reply_to_post_number": 20,
      "like_count": 0
    },
    {
      "id": 92367,
      "post_number": 22,
      "username": "kapo",
      "name": "",
      "avatar_template": "/user_avatar/peshkupauje.com/kapo/{size}/4005_2.png",
      "created_at": "2019-06-06T20:53:28.730Z",
      "cooked": "<p>Të gjithë po pyesin ku i gjeti “BILD” përgjimet. Ka gisht PD në përgjimet që “BILD” ka marrë?</p>\n<p>Edi Paloka: Po si mund të ketë gisht PD. E dini cfarë i ka thënë delegacionit tonë në Gjermani? Këto nuk janë asgjë nga të dhënat dhe faktet që kemi ne .</p>",
      "reply_to_post_number": null,
      "like_count": 0
    },
    {
      "id": 92368,
      "post_number": 23,
      "username": "kapo",
      "name": "",
      "avatar_template": "/user_avatar/peshkupauje.com/kapo/{size}/4005_2.png",
      "created_at": "2019-06-06T20:54:31.946Z",
      "cooked": "<p><a href=\"http://www.panorama.com.al/vangjush-dako-nxjerr-bllof-edi-ramen-avdylajt-simpatizante-te-partise-socialiste/\" class=\"onebox\" target=\"_blank\" rel=\"nofollow noopener\">http://www.panorama.com.al/vangjush-dako-nxjerr-bllof-edi-ramen-avdylajt-simpatizante-te-partise-socialiste/</a></p>",
      "reply_to_post_number": 21,
      "like_count": 0
    },
    {
      "id": 92369,
      "post_number": 24,
      "username": "STALKER",
      "name": "",
      "avatar_template": "/user_avatar/peshkupauje.com/stalker/{size}/2135_2.png",
      "created_at": "2019-06-06T20:54:50.726Z",
      "cooked": "<p>Hanibali e ka kot: 21 janar tjeter nuk do të kete. Kulla…</p>\n<aside class=\"onebox whitelistedgeneric\">\n  <header class=\"source\">\n      <a href=\"https://www.javanews.al/kulla-e-barit-nuk-do-te-digjet/\" target=\"_blank\" rel=\"nofollow noopener\">Javanews.al</a>\n  </header>\n  <article class=\"onebox-body\">\n    <div class=\"aspect-image\" style=\"--aspect-ratio:750/450;\"><img src=\"https://peshkupauje.com/uploads/default/original/2X/a/ae461b9edab9346a669466b47ea5c177ce38c3f7.jpeg\" class=\"thumbnail\"></div>\n\n<h3><a href=\"https://www.javanews.al/kulla-e-barit-nuk-do-te-digjet/\" target=\"_blank\" rel=\"nofollow noopener\">Kulla e barit, nuk do të digjet!</a></h3>\n\n<p>Nga Sokol Balla Tirana ishte e shkretë mbrëmjen e të dielës në orët e vona. Para Kryeministrisë vetëm policë dhe makina të medias. Një vajzë që çan pa dashje rrethimin me biçikletë, policët shpejtojnë ta largojnë. Po ashtu edhe një çift mbi 50 vjeç....</p>\n\n\n  </article>\n  <div class=\"onebox-metadata\">\n    \n    \n  </div>\n  <div style=\"clear: both\"></div>\n</aside>\n",
      "reply_to_post_number": null,
      "like_count": 0
    },
    {
      "id": 92370,
      "post_number": 25,
      "username": "STALKER",
      "name": "",
      "avatar_template": "/user_avatar/peshkupauje.com/stalker/{size}/2135_2.png",
      "created_at": "2019-06-06T20:57:44.401Z",
      "cooked": "<p>Prandaj pushtuan  studiot televizive sonte Luli dhe çunat e PDhit, sepse kishin ç’rrefenin nga turneu gjerman?<br>\n<img src=\"https://peshkupauje.com/images/emoji/apple/joy.png?v=9\" title=\":joy:\" class=\"emoji\" alt=\":joy:\"></p>",
      "reply_to_post_number": 22,
      "like_count": 0
    },
    {
      "id": 92373,
      "post_number": 26,
      "username": "kapo",
      "name": "",
      "avatar_template": "/user_avatar/peshkupauje.com/kapo/{size}/4005_2.png",
      "created_at": "2019-06-06T21:35:31.740Z",
      "cooked": "<p>Gazetari Gjekmarkaj ka debatuarr me Ramën pasi ky i fundit e ofendoi duke e etiketuar si “shërbëtor të PD dhe të Bashës”. Gjekmarkaj i është përgjigjur duke ju përgjigjur se “ti je shërbëtor i krimit të organizuar”. Debati nisi pas debatit në lidhje me përgjimet e fundit të gazetës gjermane “Bild”.</p>\n<p>Rama e ka ofenduar përgjatë gjithë kohës gazetarin ndërsa i ëshstë kundërpërgjigjur po aq ashpër. “Nuk më kërcënon ti mua, nuk ma ndjen fare për ty”, kjo sjellë edhe reagimin e Ramës duke përsëitur se gjuha e tij është ajo baltoviës të opozitës në Parlament.</p>\n<p>Debati</p>\n<p>Gjekmarkaj: Ju duhet të mbani përgjegjësi për këto që ndodhin në Shqipëri, ku kriminelët vendosin për deputetët dhe kryetarët e bashkive.</p>\n<p>Rama: Ju jeni një shërbëtor i revolucionit.</p>\n<p>Gjekmarkaj: Nëse unë jam shërbëtor, atëherë ju jeni shërbëtor i krimit të organizuar.</p>\n<p>Rama: Këto janë ca përgjime që janë mbajtur gjatë për të bërë presion që të vijë në studio disa njerëz si ky (Drejton gishtin nga Gjekmarkaj).</p>\n<p>Gjekmarkaj: Mos më drejto mua gishtin ki respekt, se s’të ka frikë njeri, mos kërcëno.</p>\n<p>Rama: Unë nuk kërcënoj, unë nuk kërcënoj, unë nuk kërcënoj (Ndërkohë i bie tavolinës me grushta</p>",
      "reply_to_post_number": 25,
      "like_count": 0
    },
    {
      "id": 92379,
      "post_number": 27,
      "username": "varik",
      "name": "varianti kohor",
      "avatar_template": "/user_avatar/peshkupauje.com/varik/{size}/115_2.png",
      "created_at": "2019-06-06T22:57:17.157Z",
      "cooked": "<p>Ti lere karrigen braces</p>",
      "reply_to_post_number": 26,
      "like_count": 0
    },
    {
      "id": 92420,
      "post_number": 28,
      "username": "STALKER",
      "name": "",
      "avatar_template": "/user_avatar/peshkupauje.com/stalker/{size}/2135_2.png",
      "created_at": "2019-06-07T22:22:15.626Z",
      "cooked": "<p>Po qe ndodh të kete edhe ndonje gazetarí investiguese në Shqiperi?</p>\n<aside class=\"onebox whitelistedgeneric\">\n  <header class=\"source\">\n      <img src=\"https://peshkupauje.com/uploads/default/original/2X/c/c72dc12bf67ed9a131c79753a51e03c48aa28562.png\" class=\"site-icon\" width=\"32\" height=\"32\">\n      <a href=\"https://realstory.al/sokol-balla-kater-rruget-e-shijakut/\" target=\"_blank\" title=\"03:23PM - 07 June 2019\" rel=\"nofollow noopener\">Real Story – 7 Jun 19</a>\n  </header>\n  <article class=\"onebox-body\">\n    <div class=\"aspect-image\" style=\"--aspect-ratio:800/532;\"><img src=\"https://peshkupauje.com/uploads/default/original/2X/a/a7b7a77cfb82895d8018ae0fd4d516c5090f9094.jpeg\" class=\"thumbnail\"></div>\n\n<h3><a href=\"https://realstory.al/sokol-balla-kater-rruget-e-shijakut/\" target=\"_blank\" rel=\"nofollow noopener\">Sokol Balla: Katër “rrugët” e Shijakut - Real Story</a></h3>\n\n<p>Nëse hyn në Shijak – nga secila prej katër rrugëve tëtij – e kupton se bëhet fjalë jo për një qytet, por për një fshat. Një fshat të madh dhe të pasur. Aty mbizotërojnë serviset e makinave, noteritë ku bëhen kontratat për shitjen dhe blerjen e tyre,...</p>\n\n\n  </article>\n  <div class=\"onebox-metadata\">\n    \n    \n  </div>\n  <div style=\"clear: both\"></div>\n</aside>\n",
      "reply_to_post_number": null,
      "like_count": 0
    },
    {
      "id": 92423,
      "post_number": 29,
      "username": "InkuizitoriMoth",
      "name": "..... ......",
      "avatar_template": "/user_avatar/peshkupauje.com/inkuizitorimoth/{size}/7035_2.png",
      "created_at": "2019-06-07T22:52:53.059Z",
      "cooked": "<p>Po qe ndodh qe nje regjizor i modh investigativ Francis Coppola ka bo filmin e modh “Padrino” (e lu Marloni), i cili tregon se bota e krimit qendron me lart moralisht se bota politike? Dmth qe Marloni qendron me lart se çdo politikan! (bile Marloni qendron ngambrapa çdo politikani)</p>",
      "reply_to_post_number": null,
      "like_count": 0
    },
    {
      "id": 92424,
      "post_number": 30,
      "username": "InkuizitoriMoth",
      "name": "..... ......",
      "avatar_template": "/user_avatar/peshkupauje.com/inkuizitorimoth/{size}/7035_2.png",
      "created_at": "2019-06-07T23:06:58.275Z",
      "cooked": "<div class=\"lazyYT\" data-youtube-id=\"Ye12fBU00jc\" data-youtube-title=\"La mitica scena iniziale del Padrino\" data-width=\"480\" data-height=\"270\" data-parameters=\"feature=oembed&amp;wmode=opaque&amp;start=41\"></div>",
      "reply_to_post_number": 29,
      "like_count": 0
    }
  ]
}